{
  "total_return": 0.018543119500000146,
  "annual_return": 0.05603610048929086,
  "max_drawdown": -0.006004306841797907,
  "sharpe_ratio": 2.7687644808769085,
  "final_value": 509271.5597500001,
  "dca_buy_count": 9,
  "dca_sell_count": 0,
  "t_buy_count": 3,
  "t_sell_count": 3,
  "t_profit": 1456.4827200000036,
  "dca_cash": 260563.27703000003,
  "t_cash": 151456.48272000003,
  "dca_value": 97251.8,
  "t_value": 0.0,
  "annual_returns": [
    {
      "year": 2025,
      "return": 0.0063838590200000905,
      "profit": 3191.9295100000454,
      "start_value": 500000.0,
      "end_value": 503191.92951000005
    },
    {
      "year": 2026,
      "return": 0.008056589558694297,
      "profit": 4070.2000000000116,
      "start_value": 505201.35975000006,
      "end_value": 509271.5597500001
    }
  ],
  "data_start_date": "2025-09-15",
  "data_end_date": "2026-01-16"
}