{
  "total_return": 0.7102875496740741,
  "annual_return": 0.1885510581491996,
  "max_drawdown": -0.3863100666036216,
  "sharpe_ratio": 0.2822851107488293,
  "final_value": 855143.7748370371,
  "dca_buy_count": 67,
  "dca_sell_count": 3,
  "t_buy_count": 43,
  "t_sell_count": 43,
  "t_profit": -2486.0176999999385,
  "dca_cash": 5585.348092592669,
  "t_cash": 147513.98230000003,
  "dca_value": 702044.4444444444,
  "t_value": 0.0,
  "annual_returns": [
    {
      "year": 2022,
      "return": 0.0,
      "profit": 0.0,
      "start_value": 500000.0,
      "end_value": 500000.0
    },
    {
      "year": 2023,
      "return": 0.27314564793181284,
      "profit": 136570.4143296295,
      "start_value": 499991.1782000001,
      "end_value": 636561.5925296296
    },
    {
      "year": 2024,
      "return": 0.123073778271494,
      "profit": 78668.22720370372,
      "start_value": 639195.6784666667,
      "end_value": 717863.9056703704
    },
    {
      "year": 2025,
      "return": 0.09695788390268556,
      "profit": 70272.37323333335,
      "start_value": 724772.1423444445,
      "end_value": 795044.5155777779
    },
    {
      "year": 2026,
      "return": 0.05236078899602312,
      "profit": 42548.14814814809,
      "start_value": 812595.626688889,
      "end_value": 855143.7748370371
    }
  ],
  "data_start_date": "2022-12-09",
  "data_end_date": "2026-01-16"
}