{
  "total_return": 0.6266145768814818,
  "annual_return": 0.17180719823937673,
  "max_drawdown": -0.4658627965922315,
  "sharpe_ratio": 0.6115653602538046,
  "final_value": 813307.2884407409,
  "dca_buy_count": 68,
  "dca_sell_count": 3,
  "t_buy_count": 41,
  "t_sell_count": 41,
  "t_profit": 14418.477300000057,
  "dca_cash": 9944.366696296278,
  "t_cash": 164418.4773000001,
  "dca_value": 638944.4444444445,
  "t_value": 0.0,
  "annual_returns": [
    {
      "year": 2022,
      "return": 0.0,
      "profit": 0.0,
      "start_value": 500000.0,
      "end_value": 500000.0
    },
    {
      "year": 2023,
      "return": -0.002483836814515737,
      "profit": -1241.912299999909,
      "start_value": 499997.5412,
      "end_value": 498755.62890000007
    },
    {
      "year": 2024,
      "return": -0.18667667037719274,
      "profit": -91886.99100000004,
      "start_value": 492225.3585000001,
      "end_value": 400338.36750000005
    },
    {
      "year": 2025,
      "return": 0.7601536344365668,
      "profit": 292127.86245185183,
      "start_value": 384301.0797000001,
      "end_value": 676428.942151852
    },
    {
      "year": 2026,
      "return": 0.186604335235148,
      "profit": 127899.97591851861,
      "start_value": 685407.3125222223,
      "end_value": 813307.2884407409
    }
  ],
  "data_start_date": "2022-12-23",
  "data_end_date": "2026-01-16"
}