{
  "total_return": 0.151980882155556,
  "annual_return": 0.047404345717616314,
  "max_drawdown": -0.238750207277279,
  "sharpe_ratio": 0.19584425723957483,
  "final_value": 575990.441077778,
  "dca_buy_count": 77,
  "dca_sell_count": 3,
  "t_buy_count": 46,
  "t_sell_count": 46,
  "t_profit": 1036.5066000000643,
  "dca_cash": 1953.6381814815613,
  "t_cash": 151036.50660000008,
  "dca_value": 423000.29629629635,
  "t_value": 0.0,
  "annual_returns": [
    {
      "year": 2022,
      "return": 0.0,
      "profit": 0.0,
      "start_value": 500000.0,
      "end_value": 500000.0
    },
    {
      "year": 2023,
      "return": 0.06363301136277082,
      "profit": 31816.324900000123,
      "start_value": 499997.159,
      "end_value": 531813.4839000001
    },
    {
      "year": 2024,
      "return": 0.08521061244375726,
      "profit": 44137.97170740756,
      "start_value": 517986.7911000001,
      "end_value": 562124.7628074076
    },
    {
      "year": 2025,
      "return": 0.004012225295734413,
      "profit": 2209.9222518517636,
      "start_value": 550797.1484555558,
      "end_value": 553007.0707074075
    },
    {
      "year": 2026,
      "return": 0.03042125414029181,
      "profit": 17005.03703703708,
      "start_value": 558985.4040407409,
      "end_value": 575990.441077778
    }
  ],
  "data_start_date": "2022-12-28",
  "data_end_date": "2026-01-16"
}