{
  "total_return": -0.19423561611111043,
  "annual_return": -0.041736167390849066,
  "max_drawdown": -0.6946691222930882,
  "sharpe_ratio": -0.11347316334242398,
  "final_value": 402882.1919444448,
  "dca_buy_count": 83,
  "dca_sell_count": 3,
  "t_buy_count": 80,
  "t_sell_count": 80,
  "t_profit": -9637.183699999903,
  "dca_cash": 7212.264533333502,
  "t_cash": 140362.81630000018,
  "dca_value": 255307.11111111107,
  "t_value": 0.0,
  "annual_returns": [
    {
      "year": 2020,
      "return": 0.0,
      "profit": 0.0,
      "start_value": 500000.0,
      "end_value": 500000.0
    },
    {
      "year": 2021,
      "return": 0.25352860356391466,
      "profit": 126763.62410000002,
      "start_value": 499997.32700000005,
      "end_value": 626760.9511000001
    },
    {
      "year": 2022,
      "return": 0.13772766070631537,
      "profit": 86578.48507777776,
      "start_value": 628620.8931000001,
      "end_value": 715199.3781777779
    },
    {
      "year": 2023,
      "return": -0.46581248659122126,
      "profit": -344229.11535555543,
      "start_value": 738986.448977778,
      "end_value": 394757.33362222253
    },
    {
      "year": 2024,
      "return": -0.1825637669593305,
      "profit": -70877.62383333337,
      "start_value": 388234.8891777781,
      "end_value": 317357.2653444447
    },
    {
      "year": 2025,
      "return": 0.07384532022514244,
      "profit": 23228.926600000006,
      "start_value": 314561.9320111114,
      "end_value": 337790.8586111114
    },
    {
      "year": 2026,
      "return": 0.18290817852698357,
      "profit": 62296.0,
      "start_value": 340586.1919444448,
      "end_value": 402882.1919444448
    }
  ],
  "data_start_date": "2020-12-24",
  "data_end_date": "2026-01-16"
}