{
  "total_return": 0.05849854214000027,
  "annual_return": 0.08113393134556524,
  "max_drawdown": -0.02446733040246481,
  "sharpe_ratio": 1.8992816472626524,
  "final_value": 529249.2710700001,
  "dca_buy_count": 24,
  "dca_sell_count": 0,
  "t_buy_count": 9,
  "t_sell_count": 9,
  "t_profit": 1423.2738200000204,
  "dca_cash": 111585.99725000009,
  "t_cash": 151423.27382000006,
  "dca_value": 266240.0,
  "t_value": 0.0,
  "annual_returns": [
    {
      "year": 2025,
      "return": 0.04508847170000034,
      "profit": 22544.235850000172,
      "start_value": 500000.0,
      "end_value": 522544.2358500002
    },
    {
      "year": 2026,
      "return": 0.005135360905445344,
      "profit": 2704.0,
      "start_value": 526545.2710700001,
      "end_value": 529249.2710700001
    }
  ],
  "data_start_date": "2025-04-25",
  "data_end_date": "2026-01-16"
}