{
  "total_return": -0.020484304099999833,
  "annual_return": -0.03838587628447254,
  "max_drawdown": -0.06503364691003626,
  "sharpe_ratio": -0.720491978197128,
  "final_value": 489757.8479500001,
  "dca_buy_count": 17,
  "dca_sell_count": 0,
  "t_buy_count": 6,
  "t_sell_count": 6,
  "t_profit": 1214.164320000018,
  "dca_cash": 180561.28363000005,
  "t_cash": 151214.16432000004,
  "dca_value": 157982.40000000002,
  "t_value": 0.0,
  "annual_returns": [
    {
      "year": 2025,
      "return": -0.05251133693999995,
      "profit": -26255.668469999975,
      "start_value": 500000.0,
      "end_value": 473744.33153
    },
    {
      "year": 2026,
      "return": 0.016099464938826285,
      "profit": 7759.908920000016,
      "start_value": 481997.93903000007,
      "end_value": 489757.8479500001
    }
  ],
  "data_start_date": "2025-07-07",
  "data_end_date": "2026-01-16"
}